encrypted_bucket/__init__.py
encrypted_bucket/py.typed
encrypted_bucket/_jsii/__init__.py
encrypted_bucket/_jsii/encrypted-bucket@0.0.9.jsii.tgz
encrypted_bucket-0.0.9.dist-info/LICENSE
encrypted_bucket-0.0.9.dist-info/METADATA
encrypted_bucket-0.0.9.dist-info/WHEEL
encrypted_bucket-0.0.9.dist-info/top_level.txt
encrypted_bucket-0.0.9.dist-info/RECORD
