Metadata-Version: 2.1
Name: encrypted-bucket
Version: 0.0.9
Summary: A CDK construct for encrypted S3 Buckets
Home-page: https://github.com/sbstjn/cdk-encrypted-bucket.git
Author: Sebastian Müller<mail@sbstjn.com>
License: MIT
Project-URL: Source, https://github.com/sbstjn/cdk-encrypted-bucket.git
Platform: UNKNOWN
Classifier: Intended Audience :: Developers
Classifier: Operating System :: OS Independent
Classifier: Programming Language :: JavaScript
Classifier: Programming Language :: Python :: 3 :: Only
Classifier: Programming Language :: Python :: 3.6
Classifier: Programming Language :: Python :: 3.7
Classifier: Programming Language :: Python :: 3.8
Classifier: Programming Language :: Python :: 3.9
Classifier: Typing :: Typed
Classifier: Development Status :: 5 - Production/Stable
Classifier: License :: OSI Approved
Requires-Python: >=3.6
License-File: LICENSE
Requires-Dist: aws-cdk-lib (<3.0.0,>=2.1.0)
Requires-Dist: constructs (<11.0.0,>=10.0.5)
Requires-Dist: jsii (<2.0.0,>=1.57.0)
Requires-Dist: publication (>=0.0.3)
